instr_mem.v
module instr_mem (
    clk, read_addr, read_data
);
    input clk;
    input [3:0] read_addr;
    output reg [4:0] read_data;

    reg [4:0] instr_mem [15:0];

    initial begin
        // Read the program from the file
        $readmemb("instr.txt", instr_mem);
    end

    always @(posedge clk ) begin
        read_data <= instr_mem[read_addr];
    end
endmodule

tb_instr_mem.v
module tb_instr_mem;
    reg clk;
    reg [3:0] in;
    wire [4:0] out;

    instr_mem dut(.clk(clk), .read_addr(in), .read_data(out));

    always #5 clk = ~clk;

    initial begin 
        $dumpfile("instr_mem.vcd");
        $dumpvars(0,tb_instr_mem);

        clk <= 0;

        #5 in <= 4'd0;
        #10 in <= 4'd1;
        #10 in <= 4'd2;
        #10 in <= 4'd3;
        #10 in <= 4'd4;
        #10 in <= 4'd5;

        #100 $finish;
    end
    
endmodule

instr_mem.vcd
$date
	Mon Sep  4 17:35:01 2023
$end
$version
	Icarus Verilog
$end
$timescale
	1s
$end
$scope module tb_instr_mem $end
$var wire 5 ! out [4:0] $end
$var reg 1 " clk $end
$var reg 4 # in [3:0] $end
$scope module dut $end
$var wire 1 " clk $end
$var wire 4 $ read_addr [3:0] $end
$var reg 5 % read_data [4:0] $end
$upscope $end
$upscope $end
$enddefinitions $end
#0
$dumpvars
bx %
bx $
bx #
0"
bx !
$end
#5
b0 #
b0 $
1"
#10
0"
#15
b11 !
b11 %
b1 #
b1 $
1"
#20
0"
#25
b1 !
b1 %
b10 #
b10 $
1"
#30
0"
#35
b10000 !
b10000 %
b11 #
b11 $
1"
#40
0"
#45
b10 !
b10 %
b100 #
b100 $
1"
#50
0"
#55
b11 !
b11 %
b101 #
b101 $
1"
#60
0"
#65
b0 !
b0 %
1"
