output_mem.v
module output_mem (
    clk, rst, read_addr, read_data, w_en, c00, c01, c02, c03, c10, c11, c12, c13, c20, c21, c22, c23, c30, c31, c32, c33
);
    input clk;
    input rst;
    input w_en;
    input [3:0] read_addr; // 4 bits to access 2 ^ 4 = 16 locations
    input [32:0] c00, c01, c02, c03, c10, c11, c12, c13, c20, c21, c22, c23, c30, c31, c32, c33; // Direct connections from PE array

    output reg [32:0] read_data;

    // Output memory
    reg [32:0] output_mem [15:0];

    always @(posedge clk ) begin
        // Read from memory
        read_data <= output_mem[read_addr];

        if (w_en) begin 
            output_mem[0] <= c00;
            output_mem[1] <= c01;
            output_mem[2] <= c02;
            output_mem[3] <= c03;

            output_mem[4] <= c10;
            output_mem[5] <= c11;
            output_mem[6] <= c12;
            output_mem[7] <= c13;

            output_mem[8] <= c20;
            output_mem[9] <= c21;
            output_mem[10] <= c22;
            output_mem[11] <= c23;

            output_mem[12] <= c30;
            output_mem[13] <= c31;
            output_mem[14] <= c32;
            output_mem[15] <= c33;
        end
    end

endmodule

tb_output_mem.v
module tb_output_mem;
    reg clk;

    reg [3:0] read_addr;
    wire [32:0] read_data;

    output_mem dut(.clk(clk), .read_addr(read_addr), .read_data(read_data));

    always #5 clk = ~clk;

    initial begin 
        $dumpfile("output_mem.vcd");
        $dumpvars(0,tb_output_mem);

        clk <= 0;

        #5 read_addr <= 6'd0;
        #10 read_addr <= 6'd1;
        #10 read_addr <= 6'd2;
        #10 read_addr <= 6'd3;
        #10 read_addr <= 6'd4;
        #10 read_addr <= 6'd5;
        #10 read_addr <= 6'd6;
        #10 read_addr <= 6'd7;
        #10 read_addr <= 6'd8;
        #10 read_addr <= 6'd9;
        #10 read_addr <= 6'd10;
        #10 read_addr <= 6'd11;
        #10 read_addr <= 6'd12;
        #10 read_addr <= 6'd13;
        #10 read_addr <= 6'd14;
        #10 read_addr <= 6'd15;

        #200 $finish;
    end
    
endmodule

output_mem.vcd
$date
	Mon Sep  4 19:14:53 2023
$end
$version
	Icarus Verilog
$end
$timescale
	1s
$end
$scope module tb_output_mem $end
$var wire 33 ! read_data [32:0] $end
$var reg 1 " clk $end
$var reg 4 # read_addr [3:0] $end
$scope module dut $end
$var wire 1 " clk $end
$var wire 4 $ read_addr [3:0] $end
$var reg 33 % read_data [32:0] $end
$upscope $end
$upscope $end
$enddefinitions $end
#0
$dumpvars
bx %
bx $
bx #
0"
bx !
$end
#5
b0 #
b0 $
1"
#10
0"
#15
b101 !
b101 %
b1 #
b1 $
1"
#20
0"
#25
b111 !
b111 %
b10 #
b10 $
1"
#30
0"
#35
b10 !
b10 %
b11 #
b11 $
1"
#40
0"
#45
b1 !
b1 %
b100 #
b100 $
1"
#50
0"
#55
b1111 !
b1111 %
b101 #
b101 $
1"
#60
0"
#65
b110 !
b110 %
b110 #
b110 $
1"
#70
0"
#75
b100 !
b100 %
b111 #
b111 $
1"
#80
0"
#85
b1 !
b1 %
b1000 #
b1000 $
1"
#90
0"
#95
b101 !
b101 %
b1001 #
b1001 $
1"
#100
0"
#105
b1001 !
b1001 %
b1010 #
b1010 $
1"
#110
0"
#115
b110 !
b110 %
b1011 #
b1011 $
1"
#120
0"
#125
b1011 !
b1011 %
b1100 #
b1100 $
1"
#130
0"
#135
b1001 !
b1001 %
b1101 #
b1101 $
1"
#140
0"
#145
b110 !
b110 %
b1110 #
b1110 $
1"
#150
0"
#155
b1000 !
b1000 %
b1111 #
b1111 $
1"
#160
0"
#165
b1 !
b1 %
1"
